krippendorrf_graph.py
graph_krippendorrf-0.1.1.dist-info/LICENSE
graph_krippendorrf-0.1.1.dist-info/METADATA
graph_krippendorrf-0.1.1.dist-info/WHEEL
graph_krippendorrf-0.1.1.dist-info/top_level.txt
graph_krippendorrf-0.1.1.dist-info/RECORD
